pypermod/__init__.py
pypermod/config.py
pypermod/utility.py
pypermod/agents/__init__.py
pypermod/agents/cp_agent_basis.py
pypermod/agents/hyd_agents/__init__.py
pypermod/agents/hyd_agents/hyd_agent_basis.py
pypermod/agents/hyd_agents/three_comp_hyd_agent.py
pypermod/agents/hyd_agents/two_comp_hyd_agent.py
pypermod/agents/wbal_agents/__init__.py
pypermod/agents/wbal_agents/wbal_int_agent.py
pypermod/agents/wbal_agents/wbal_int_agent_fix_tau.py
pypermod/agents/wbal_agents/wbal_int_agent_skiba.py
pypermod/agents/wbal_agents/wbal_ode_agent_bartram.py
pypermod/agents/wbal_agents/wbal_ode_agent_exponential.py
pypermod/agents/wbal_agents/wbal_ode_agent_fix_tau.py
pypermod/agents/wbal_agents/wbal_ode_agent_linear.py
pypermod/agents/wbal_agents/wbal_ode_agent_skiba.py
pypermod/agents/wbal_agents/wbal_ode_agent_weigend.py
pypermod/data_structure/__init__.py
pypermod/data_structure/athlete.py
pypermod/data_structure/activities/__init__.py
pypermod/data_structure/activities/activity.py
pypermod/data_structure/activities/activity_types.py
pypermod/data_structure/activities/protocol_types.py
pypermod/data_structure/activities/data_formats/__init__.py
pypermod/data_structure/activities/data_formats/bbb_measured.py
pypermod/data_structure/activities/data_formats/protocol_time_stamps.py
pypermod/data_structure/activities/data_formats/time_series.py
pypermod/data_structure/activities/type_classes/__init__.py
pypermod/data_structure/activities/type_classes/srm_bbb_test.py
pypermod/data_structure/activities/type_classes/strava_bike.py
pypermod/data_structure/helper/__init__.py
pypermod/data_structure/helper/simple_constant_effort_measures.py
pypermod/fitter/__init__.py
pypermod/fitter/cp_to_tte_fitter.py
pypermod/fitter/tau_fitter.py
pypermod/processing/__init__.py
pypermod/processing/time_series_processing.py
pypermod/simulator/__init__.py
pypermod/simulator/simulator_basis.py
pypermod/simulator/study_simulator.py
pypermod/simulator/three_comp_hyd_simulator.py
pypermod-1.3.0.dist-info/LICENSE
pypermod-1.3.0.dist-info/METADATA
pypermod-1.3.0.dist-info/WHEEL
pypermod-1.3.0.dist-info/top_level.txt
pypermod-1.3.0.dist-info/RECORD
