Metadata-Version: 2.1
Name: pypermod
Version: 1.3.0
Summary: A performance modeling package that provides various tools to predict energy expenditure and recovery dynamics of an athlete
Home-page: https://github.com/faweigend/pypermod
Author: Fabian Weigend
Author-email: fabian.weigend@westernsydney.edu.au
Project-URL: Bug Tracker, https://github.com/faweigend/pypermod/issues
Classifier: Programming Language :: Python :: 3
Classifier: License :: OSI Approved :: MIT License
Classifier: Operating System :: OS Independent
Requires-Python: >=3.6
License-File: LICENSE
Requires-Dist: matplotlib
Requires-Dist: scipy
Requires-Dist: scikit-learn
Requires-Dist: numpy
Requires-Dist: fitparse
